{"ticker": "TXN", "generated_at": "2026-03-18T17:33:29.244759Z", "tier": "platinum", "version": "1.0", "profile": {"name": "Texas Instruments Incorporated", "sector": "Technology", "industry": "Semiconductors", "market_cap": 176425025536, "employees": 33000, "country": "United States", "exchange": "NMS"}, "price": {"current": 193.78, "previous_close": 194.45, "change_pct": -0.35, "day_high": 195.54, "day_low": 192.53, "volume": 1529390, "avg_volume": 7633705}, "technicals": {"sma_20": 203.56, "sma_50": 205.15, "sma_200": null, "price_vs_sma20": -4.81, "price_vs_sma50": -5.54, "rsi_14": 25.54, "high_52w": 226.56, "low_52w": 152.34, "pct_from_52w_high": -14.47}, "valuation": {"pe_trailing": 35.620403, "pe_forward": 24.501808, "peg_ratio": null, "pb_ratio": 10.800078, "ps_ratio": 9.977662, "ev_ebitda": 23.169, "ev_revenue": 10.54, "price_to_fcf": null}, "fundamentals": {"revenue": 17681999872, "revenue_growth": 0.104, "gross_margin": 0.57023996, "operating_margin": 0.34027, "profit_margin": 0.28283, "roe": 0.30148, "roa": 0.10925, "debt_to_equity": 90.819, "current_ratio": 4.353, "free_cash_flow": -300624992, "eps_trailing": 5.44, "eps_forward": 7.9086, "beta": 0.979}, "dividend": {"yield": 2.92, "rate": 5.68, "payout_ratio": 1.0092, "ex_date": "1769731200"}, "gurufocus": {"rankings": {"gf_score": 88.0, "financial_strength": 7.0, "profitability_rank": 8.0, "growth_rank": 7.0, "value_rank": 7.0, "momentum_rank": 10.0, "predictability_rank": 1.0, "piotroski_f": null, "altman_z": null}, "valuations": {"gf_value": null, "dcf_value": null, "graham_number": null, "peter_lynch_value": null, "gf_current_price": 173.49, "price_to_gf_value": null}, "gf_fundamentals": {"roe": null, "roic": null, "revenue_growth_3y": null, "eps_growth_3y": null, "debt_to_equity": null, "interest_coverage": null, "fcf_yield": null, "dividend_yield": null}}, "analyst_targets": {"mean_target": 221.55, "median_target": 226.0, "high_target": null, "low_target": null, "upside_pct": 14.33, "num_analysts": null, "assessment": {"rating": "Hold - Slight upside", "color": "yellow"}}, "insider_activity": {"signal": "no_data", "transactions": []}, "institutional": {"institutional_pct": null, "top_holders": [{"rank": 1, "holder": "Vanguard Group Inc", "shares": 96527471, "date_reported": "2025-12-31", "pct_out": 0, "value": 18704610103}, {"rank": 2, "holder": "Blackrock Inc.", "shares": 79040582, "date_reported": "2025-12-31", "pct_out": 0, "value": 15316088294}, {"rank": 3, "holder": "State Street Corporation", "shares": 43446720, "date_reported": "2025-12-31", "pct_out": 0, "value": 8418887902}, {"rank": 4, "holder": "JPMORGAN CHASE & CO", "shares": 28324885, "date_reported": "2025-12-31", "pct_out": 0, "value": 5488654417}, {"rank": 5, "holder": "Charles Schwab Investment Management, Inc.", "shares": 24288604, "date_reported": "2025-12-31", "pct_out": 0, "value": 4706524091}], "total_institutions": null}, "estimate_revisions": {"momentum_score": 47.39, "signal": "Hold", "revision_velocity": 0.0, "trend": "Stable", "total_analysts": 37, "consensus": "Hold", "target_price": 221.55, "upside_pct": 14.33}, "earnings_quality": {"accruals_ratio": -0.0622, "accruals_flag": "GOOD", "beneish_m_score": -2.678, "beneish_flag": "UNLIKELY MANIPULATOR", "altman_z_score": 9.371, "altman_flag": "SAFE ZONE", "overall_risk": "LOW", "earnings_quality": "GOOD", "manipulation_risk": "UNLIKELY MANIPULATOR"}, "earnings_surprises": {"beat_rate": 75.0, "avg_surprise_pct": 6.1, "total_quarters": 12, "beats": 9, "misses": 0, "avg_drift_1d": 0.23, "avg_drift_5d": 0.46, "last_quarter": {"quarter": "2026-01", "report_date": "2026-01-27", "eps_estimate": 1.28, "eps_actual": 1.31, "eps_surprise": 0.03, "eps_surprise_pct": 2.3, "revenue_estimate": 0, "revenue_actual": 0, "revenue_surprise": 0, "revenue_surprise_pct": 0, "beat_miss": "BEAT", "price_before": 195.32, "price_after_1d": 214.77, "price_after_3d": 215.55, "price_after_5d": 215.55, "drift_1d": 9.96, "drift_3d": 10.36, "drift_5d": 10.36}}, "composite": {"composite_score": 79.8, "rating": "Buy", "component_scores": {"valuation": 75.5, "analyst": 64.3, "earnings_quality": 100, "earnings_momentum": 75.0, "technicals": 51.1, "fundamentals": 100, "gf_score": 88.0}, "weights_used": {"valuation": 0.15, "analyst": 0.15, "earnings_quality": 0.1, "earnings_momentum": 0.1, "technicals": 0.1, "fundamentals": 0.15, "gf_score": 0.15}, "coverage": 7, "max_coverage": 10}, "_meta": {"elapsed_seconds": 2.67, "sections_populated": 14, "total_sections": 16}}